ukflib
