Metadata-Version: 1.1
Name: ukflib
Version: 0.0.3
Summary: An Unscented Kalman Filter library that allows for nonadditive process and measurement noise
Home-page: https://github.com/sciencectn/ukflib
Author: Chris Taylor
Author-email: sciencectn@gmail.com
License: UNKNOWN
Keywords: ukf unscented kalman filter
Platform: UNKNOWN
Classifier: Programming Language :: Python :: 3.6
Classifier: Programming Language :: Python :: 2.7
Classifier: Topic :: Scientific/Engineering
Classifier: Intended Audience :: Science/Research
